get_biomes/__init__.py
get_biomes/__main__.py
get_biomes/_version.py
get_biomes/defaults.py
get_biomes/download.py
get_biomes/search.py
get_biomes/utils.py
get_biomes-0.1.4.dist-info/LICENSE
get_biomes-0.1.4.dist-info/METADATA
get_biomes-0.1.4.dist-info/WHEEL
get_biomes-0.1.4.dist-info/entry_points.txt
get_biomes-0.1.4.dist-info/top_level.txt
get_biomes-0.1.4.dist-info/RECORD
