Metadata-Version: 2.1
Name: get-biomes
Version: 0.1.4
Summary: A simple tool to get biomes related data from MGnify and ENA
Home-page: https://github.com/genomewalker/get-biomes
Author: Antonio Fernandez-Guerra
Author-email: antonio@metagenomics.eu
License: GNUv3
Keywords: get-biomes
Platform: UNKNOWN
Classifier: Programming Language :: Python :: 3.9
License-File: LICENSE
Requires-Dist: pandas (>=1.3.3)
Requires-Dist: tqdm (>=4.50.0)
Requires-Dist: jsonapi-client
Requires-Dist: requests
Requires-Dist: tqdm
